<?xml version="1.0" encoding="UTF-8"?>
<!DOCTYPE mapper PUBLIC "-//mybatis.org//DTD Mapper 3.0//EN" "http://mybatis.org/dtd/mybatis-3-mapper.dtd">
<mapper namespace="com.alex.demo.mybatis.mapper.SalariesMapper">
  <resultMap id="BaseResultMap" type="com.alex.demo.mybatis.model.Salaries">
    <!--
      WARNING - @mbg.generated
      This element is automatically generated by MyBatis Generator, do not modify.
      This element was generated on Tue May 28 14:24:28 CST 2019.
    -->
    <result column="emp_no" jdbcType="INTEGER" property="empNo" />
    <result column="salary" jdbcType="INTEGER" property="salary" />
    <result column="from_date" jdbcType="DATE" property="fromDate" />
    <result column="to_date" jdbcType="DATE" property="toDate" />
  </resultMap>
  <insert id="insert" parameterType="com.alex.demo.mybatis.model.Salaries">
    <!--
      WARNING - @mbg.generated
      This element is automatically generated by MyBatis Generator, do not modify.
      This element was generated on Tue May 28 14:24:28 CST 2019.
    -->
    insert into salaries (emp_no, salary, from_date, 
      to_date)
    values (#{empNo,jdbcType=INTEGER}, #{salary,jdbcType=INTEGER}, #{fromDate,jdbcType=DATE}, 
      #{toDate,jdbcType=DATE})
  </insert>
  <select id="selectAll" resultMap="BaseResultMap">
    <!--
      WARNING - @mbg.generated
      This element is automatically generated by MyBatis Generator, do not modify.
      This element was generated on Tue May 28 14:24:28 CST 2019.
    -->
    select emp_no, salary, from_date, to_date
    from salaries
  </select>
</mapper>